file_finder/cli.py
file_finder/constants.py
file_finder/exceptions.py
file_finder/finder.py
file_finder/utils.py
ffinder-0.2.0.dist-info/METADATA
ffinder-0.2.0.dist-info/WHEEL
ffinder-0.2.0.dist-info/entry_points.txt
ffinder-0.2.0.dist-info/RECORD
