Metadata-Version: 2.1
Name: ffinder
Version: 0.2.0
Summary: 
Author: Miguel Freitas
Author-email: miguel_flj@id.uff.br
Requires-Python: >=3.11,<4.0
Classifier: Programming Language :: Python :: 3
Classifier: Programming Language :: Python :: 3.11
Requires-Dist: click (>=8.1.7,<9.0.0)
Requires-Dist: tabulate (>=0.9.0,<0.10.0)
